{
    "bibitems": [
    ],
    "bibtexfiles": [
        "/Users/zewen/Nutstore Files/Potential Paper/# Accepted/[Sinica] [Zewen] Error-informed Aggregation for GP/arXiv/ref.bib#ref"
    ],
    "childdocs": [
    ],
    "filename": "/Users/zewen/Nutstore Files/Potential Paper/# Accepted/[Sinica] [Zewen] Error-informed Aggregation for GP/arXiv/main.tex",
    "labels": [
        "eqn_prediction_error_derive1",
        "eqn_aggregated_prediction_error_bound_all",
        "sec_conclusion",
        "eq_phi_aEIGP",
        "eq_aEIGP_weight_generaliztion",
        "eqn_GP_prediction",
        "eq_lambda",
        "eqn_aggregation_weights_aEIGP",
        "eqn_GP_prediction_e",
        "lemma_prediction_loss",
        "eqn_aggregation_weights_gEIGP",
        "eqn_GP_variance",
        "eq_indexSet",
        "eq_mu_f",
        "eq_mu_tildemu",
        "eq_aggregation_poe",
        "eq_delete_x",
        "alg_errorUpdate",
        "fig_predictTime_8",
        "prop_mu",
        "eq_aggregation_bcm",
        "eqn_concatenated_prediction_error_outer_rho",
        "eq_proportional",
        "rem_f",
        "fig_toyStates",
        "eqn_prediction_error",
        "sec_sim",
        "fig_pol_agentQuantity_16",
        "eq_tradeoff_linear",
        "alg_EIDGP",
        "eq_predictionError",
        "eq_beta_delta",
        "eq_e_i_j2",
        "eq_tilde_h",
        "eqn_posterior_bound",
        "table_predictionTime",
        "eqn_prediction_error_derive",
        "eq_tilde_mu",
        "subsec_Benchmarks",
        "eq_EIGP_framework",
        "fig_benchmerks_16agents",
        "fig_benchmerks_8agents_POL",
        "sec_ProblemState",
        "eq_kboder2",
        "eqn_aggregation_variances_aEIGP",
        "sec_aEIGP_variants",
        "eq_datasetUpadate",
        "eqn_loss_outer_rho",
        "eq_e_i_j",
        "subsec_GPR",
        "fig_predictTime_16",
        "eq_Kmatrix2",
        "eqn_aggregated_prediction_error_bound",
        "fig_toyData",
        "fig_benchmerks_8agents_KIN40K",
        "eq_phi_gEIGP",
        "eq_hat_varepsilon",
        "fig_predictionTime_toy",
        "eq_tildeW",
        "subsec_toyExample",
        "fig_kin40k_agentQuantity_8",
        "eqn_concatenated_measurement_noise_outer_rho",
        "ass_GP",
        "subsec_regressionBenchmarks",
        "ass_dataset",
        "lemma_prediction_error",
        "eq_distanceAwareError",
        "theorem_aggregated_prediction_error_bound",
        "fig_agentQuantity_toy",
        "subsec_EIGP",
        "sec_EIGP",
        "eqn_loss_rho"
    ],
    "modified": "Sat Jan 10 17:58:20 2026",
    "packages": [
        "#lipsum",
        "journal#class-IEEEtran",
        "journal#latex-document",
        "journal#tex",
        "#chngcntr",
        "#url",
        "#multirow",
        "#verbatim",
        "#algorithm",
        "#stfloats",
        "#xcolor",
        "#cite",
        "#graphicx",
        "#enumitem",
        "#amsfonts",
        "#amsmath",
        "capitalise#cleveref",
        "#float",
        "#verbatim",
        "#pgfplots",
        "#tikz",
        "#fp",
        "#algorithmic",
        "caption=false,font=normalsize,labelfont=sf,textfont=sf#subfig",
        "#textcomp",
        "#bm",
        "#mathrsfs",
        "#amssymb",
        "#makecell",
        "#array",
        "#booktabs"
    ],
    "refs": [
        "eqn_prediction_error_derive1",
        "eqn_posterior_bound",
        "eqn_posterior_bound",
        "eqn_prediction_error_derive1",
        "ass_GP",
        "ass_dataset",
        "eq_delete_x",
        "eqn_GP_prediction",
        "eq_predictionError",
        "eqn_loss_rho",
        "ass_GP",
        "fig_toyData",
        "eq_e_i_j2",
        "eq_tildeW",
        "fig_agentQuantity_toy",
        "eq_beta_delta",
        "fig_pol_agentQuantity_16",
        "fig_kin40k_agentQuantity_8",
        "alg_errorUpdate",
        "ass_dataset",
        "eqn_aggregation_weights_aEIGP",
        "eqn_aggregation_weights_gEIGP",
        "fig_pol_agentQuantity_16",
        "fig_kin40k_agentQuantity_8",
        "ass_GP",
        "ass_dataset",
        "eqn_GP_variance",
        "eqn_GP_prediction",
        "eqn_GP_prediction_e",
        "eqn_GP_prediction",
        "fig_benchmerks_16agents",
        "subsec_Benchmarks",
        "fig_toyData",
        "prop_mu",
        "eq_phi_aEIGP",
        "eq_hat_varepsilon",
        "eq_datasetUpadate",
        "fig_agentQuantity_toy",
        "eqn_GP_prediction",
        "eqn_loss_outer_rho",
        "eqn_concatenated_measurement_noise_outer_rho",
        "eqn_concatenated_prediction_error_outer_rho",
        "alg_EIDGP",
        "eq_delete_x",
        "table_predictionTime",
        "fig_toyStates",
        "fig_predictionTime_toy",
        "eqn_aggregation_variances_aEIGP",
        "eq_tildeW",
        "eq_hat_varepsilon",
        "lemma_prediction_error",
        "eq_mu_f",
        "eqn_aggregation_weights_gEIGP",
        "eq_phi_gEIGP",
        "ass_dataset",
        "ass_GP",
        "eq_distanceAwareError",
        "eq_aggregation_bcm",
        "eq_aggregation_poe",
        "lemma_prediction_loss",
        "eqn_posterior_bound",
        "eq_distanceAwareError",
        "eq_indexSet",
        "eq_e_i_j",
        "eqn_GP_prediction_e",
        "ass_dataset",
        "alg_errorUpdate",
        "sec_EIGP",
        "subsec_GPR",
        "eq_aggregation_poe",
        "eq_tradeoff_linear",
        "fig_toyData",
        "fig_benchmerks_8agents_POL",
        "fig_benchmerks_8agents_KIN40K",
        "eq_tilde_mu",
        "eq_e_i_j",
        "lemma_prediction_loss",
        "sec_sim",
        "eqn_loss_outer_rho",
        "eq_lambda",
        "fig_predictTime_16",
        "fig_predictTime_8",
        "sec_aEIGP_variants",
        "eq_tildeW",
        "lemma_prediction_error",
        "eq_tildeW",
        "eqn_GP_variance",
        "ass_dataset",
        "sec_conclusion",
        "sec_sim",
        "sec_EIGP",
        "sec_ProblemState",
        "eq_EIGP_framework",
        "lemma_prediction_loss",
        "eq_mu_f",
        "eq_mu_tildemu",
        "eqn_aggregation_weights_aEIGP",
        "eqn_aggregation_weights_gEIGP",
        "eq_EIGP_framework",
        "lemma_prediction_error",
        "eq_aggregation_bcm",
        "table_predictionTime",
        "eqn_aggregation_weights_aEIGP",
        "eq_phi_aEIGP",
        "eq_distanceAwareError",
        "eq_phi_aEIGP",
        "eqn_aggregation_weights_gEIGP",
        "eqn_aggregated_prediction_error_bound_all",
        "eqn_aggregated_prediction_error_bound",
        "eq_EIGP_framework",
        "eqn_aggregation_weights_aEIGP",
        "eqn_aggregation_weights_gEIGP"
    ],
    "toc": [
        "2#Introduction#174",
        "2#Preliminaries and Problem Statement#216",
        "3#Notation and Graph Theory#218",
        "4#Notation#219",
        "4#Graph Theory#228",
        "3#Objective#231",
        "3#Gaussian Process Regression#249",
        "4#Training Dataset#250",
        "4#Online Learning with GPs#260",
        "2#Error-Informed Cooperative Learning#285",
        "3#Error-Informed Prediction Quantification#286",
        "3#Model Update Strategy#425",
        "3#Error-informed Gaussian Process Regression#487",
        "4#Greedy EIGP#503",
        "4#Adaptive EIGP#524",
        "3#Prediction Guarantee#610",
        "2#Numerical Demonstration#699",
        "3#Toy Example#703",
        "3#Benchmarks#780",
        "2#Conclusion#813",
        "2#Generalization of aEIGP#829",
        "2#Numerical Results#917",
        "3#Simulation Configuration#920",
        "3#Additional Simulation Results#925"
    ],
    "usercommands": [
        [
            "\\CASE",
            "\\CASE{}"
        ],
        [
            "",
            "\\nu_{\\text{Log}}"
        ],
        [
            "",
            "\\mathbb{X}"
        ],
        [
            "",
            "\\bm{x}"
        ],
        [
            "",
            "\\mathbb{D}"
        ],
        [
            "",
            "\\boldsymbol{x}"
        ],
        [
            "",
            "\\mu_s"
        ],
        [
            "",
            "\\sum_{s=1}"
        ],
        [
            "",
            "\\boldsymbol{x}"
        ],
        [
            "",
            "\\hat{f}"
        ],
        [
            "",
            "\\delta_n"
        ],
        [
            "",
            "\\delta_n"
        ],
        [
            "",
            "\\sigma_{\\omega}"
        ],
        [
            "",
            "\\beta_{\\delta}"
        ],
        [
            "\\{",
            "\\{"
        ],
        [
            "",
            "\\mathbb{R}"
        ],
        [
            "",
            "\\boldsymbol{x}"
        ],
        [
            "",
            "\\mathcal{N}"
        ],
        [
            "",
            "\\bar{\\mathcal{N}}"
        ],
        [
            "",
            "\\boldsymbol{x}"
        ],
        [
            "",
            "\\mathcal{S}"
        ],
        [
            "",
            "\\boldsymbol{x}"
        ],
        [
            "",
            "\\sigma_{is}"
        ],
        [
            "",
            "\\sigma_{\\omega}"
        ],
        [
            "",
            "\\boldsymbol{x}"
        ],
        [
            "",
            "\\vartheta_{il}"
        ],
        [
            "",
            "\\boldsymbol{x}"
        ],
        [
            "",
            "\\varepsilon_i"
        ],
        [
            "",
            "\\delta_{\\rho}"
        ],
        [
            "",
            "\\mathbb{R}"
        ],
        [
            "",
            "\\bm{y}"
        ],
        [
            "",
            "\\mu_i"
        ],
        [
            "",
            "\\bm{\\mu}"
        ],
        [
            "",
            "\\bm{e}"
        ],
        [
            "",
            "\\boldsymbol{x}"
        ],
        [
            "",
            "\\boldsymbol{x}"
        ],
        [
            "",
            "\\boldsymbol{X}"
        ],
        [
            "",
            "\\boldsymbol{x}"
        ],
        [
            "",
            "\\boldsymbol{X}"
        ],
        [
            "",
            "\\tilde{\\boldsymbol{X}}"
        ],
        [
            "",
            "\\bm{x}"
        ],
        [
            "",
            "\\eta_i"
        ],
        [
            "",
            "\\tilde{\\eta}"
        ],
        [
            "",
            "\\bm{x}"
        ],
        [
            "",
            "\\eta_i"
        ],
        [
            "",
            "\\bm{x}"
        ],
        [
            "",
            "\\mu_{i}"
        ],
        [
            "",
            "\\bm{\\mu}"
        ],
        [
            "",
            "\\tilde{\\bm{\\mu}}"
        ],
        [
            "",
            "\\bm{x}"
        ],
        [
            "",
            "\\varepsilon_i"
        ],
        [
            "\\ENDSWITCH",
            "\\ENDSWITCH"
        ],
        [
            "",
            "\\boldsymbol{x}"
        ],
        [
            "",
            "\\sigma_l"
        ],
        [
            "",
            "\\boldsymbol{x}"
        ],
        [
            "",
            "\\tilde{w}"
        ],
        [
            "",
            "\\boldsymbol{x}"
        ],
        [
            "",
            "\\mathcal{S}"
        ],
        [
            "",
            "\\sum_{l\\in\\mathcal{S}_i(\\boldsymbol{x})}"
        ],
        [
            "",
            "\\boldsymbol{x}"
        ],
        [
            "",
            "\\tilde{\\sigma}"
        ],
        [
            "",
            "\\boldsymbol{x}"
        ],
        [
            "",
            "\\tilde{\\sigma}"
        ],
        [
            "",
            "\\boldsymbol{x}"
        ],
        [
            "",
            "\\sigma_l"
        ],
        [
            "",
            "\\boldsymbol{x}"
        ],
        [
            "",
            "\\tilde{w}"
        ],
        [
            "",
            "\\boldsymbol{x}"
        ],
        [
            "",
            "\\mathcal{S}"
        ],
        [
            "",
            "\\sum_{l\\in{\\mathcal{S}}_i(\\boldsymbol{x})}"
        ],
        [
            "",
            "\\boldsymbol{x}"
        ],
        [
            "",
            "\\tilde{\\sigma}"
        ],
        [
            "",
            "\\boldsymbol{x}"
        ],
        [
            "",
            "\\sigma_s"
        ],
        [
            "",
            "\\boldsymbol{x}"
        ],
        [
            "",
            "\\tilde{w}"
        ],
        [
            "",
            "\\boldsymbol{x}"
        ],
        [
            "",
            "\\mathbb{D}"
        ],
        [
            "",
            "\\mathcal{O}"
        ],
        [
            "",
            "\\mathcal{O}"
        ],
        [
            "",
            "\\varepsilon_i"
        ],
        [
            "",
            "\\mathbb{I}"
        ],
        [
            "",
            "\\mathbb{N}"
        ],
        [
            "",
            "\\mathbb{R}"
        ],
        [
            "",
            "\\mathbb{X}"
        ],
        [
            "",
            "\\boldsymbol{x}"
        ],
        [
            "",
            "\\mathbb{N}"
        ],
        [
            "\\mathbb",
            "\\mathbb"
        ],
        [
            "",
            "\\mathbb{X}"
        ],
        [
            "",
            "\\boldsymbol{x}"
        ],
        [
            "",
            "\\boldsymbol{x}"
        ],
        [
            "",
            "\\boldsymbol{x}"
        ],
        [
            "",
            "\\boldsymbol{f}"
        ],
        [
            "",
            "\\boldsymbol{X}"
        ],
        [
            "",
            "\\boldsymbol{K}"
        ],
        [
            "",
            "\\boldsymbol{x}"
        ],
        [
            "",
            "\\mu_i"
        ],
        [
            "",
            "\\tilde{\\mu}"
        ],
        [
            "",
            "\\boldsymbol{x}"
        ],
        [
            "",
            "\\mu_i"
        ],
        [
            "",
            "\\tilde{\\mu}"
        ],
        [
            "",
            "\\boldsymbol{x}"
        ],
        [
            "",
            "\\mu_i"
        ],
        [
            "",
            "\\boldsymbol{\\mu}"
        ],
        [
            "",
            "\\tilde{\\boldsymbol{\\mu}}"
        ],
        [
            "\\commentZ",
            "\\commentZ{}"
        ],
        [
            "",
            "\\boldsymbol{x}"
        ],
        [
            "",
            "\\varepsilon_{is}"
        ],
        [
            "",
            "\\tilde{\\varepsilon}"
        ],
        [
            "",
            "\\boldsymbol{x}"
        ],
        [
            "",
            "\\phi_{is}"
        ],
        [
            "",
            "\\boldsymbol{x}"
        ],
        [
            "",
            "\\varepsilon_{is}"
        ],
        [
            "",
            "\\tilde{\\varepsilon}"
        ],
        [
            "\\argmax",
            "\\argmax"
        ],
        [
            "",
            "\\boldsymbol{Y}"
        ],
        [
            "",
            "\\boldsymbol{X}"
        ],
        [
            "",
            "\\boldsymbol{x}"
        ],
        [
            "",
            "\\mathcal{S}"
        ],
        [
            "",
            "\\boldsymbol{x}"
        ],
        [
            "",
            "\\phi_{is}"
        ],
        [
            "",
            "\\boldsymbol{x}"
        ],
        [
            "",
            "\\phi_{i}"
        ],
        [
            "",
            "\\boldsymbol{\\phi}"
        ],
        [
            "property",
            "\\end{property}"
        ],
        [
            "property",
            "\\begin{property}"
        ],
        [
            "",
            "\\bm{I}"
        ],
        [
            "\\mathbb",
            "\\mathbb"
        ],
        [
            "",
            "\\mathbb{X}"
        ],
        [
            "",
            "\\mathbb{X}"
        ],
        [
            "\\mathbb",
            "\\mathbb"
        ],
        [
            "",
            "\\mathbb{X}"
        ],
        [
            "",
            "\\boldsymbol{f}"
        ],
        [
            "",
            "\\boldsymbol{f}"
        ],
        [
            "",
            "\\sigma_{\\omega}"
        ],
        [
            "",
            "\\boldsymbol{x}"
        ],
        [
            "",
            "\\vartheta_{is}"
        ],
        [
            "",
            "\\boldsymbol{x}"
        ],
        [
            "",
            "\\tilde{w}"
        ],
        [
            "",
            "\\boldsymbol{x}"
        ],
        [
            "",
            "\\mathcal{S}"
        ],
        [
            "",
            "\\sum_{l\\in\\mathcal{S}_i(\\boldsymbol{x})}"
        ],
        [
            "remark",
            "\\end{remark}"
        ],
        [
            "remark",
            "\\begin{remark}"
        ],
        [
            "",
            "\\}_{j=1,\\dots,d}"
        ],
        [
            "",
            "\\mathbb{I}"
        ],
        [
            "",
            "\\bm{I}"
        ],
        [
            "",
            "\\mathbb{I}"
        ],
        [
            "",
            "\\bar{\\mathbb{I}}"
        ],
        [
            "",
            "\\bm{x}"
        ],
        [
            "",
            "\\bm{x}"
        ],
        [
            "",
            "\\bm{x}"
        ],
        [
            "",
            "\\bm{x}"
        ],
        [
            "",
            "\\sigma_{\\omega}"
        ],
        [
            "",
            "\\boldsymbol{x}"
        ],
        [
            "",
            "\\varepsilon_i"
        ],
        [
            "",
            "\\bm{x}"
        ],
        [
            "",
            "\\bm{f}"
        ],
        [
            "",
            "\\bm{1}"
        ],
        [
            "",
            "\\bm{x}"
        ],
        [
            "",
            "\\bm{f}"
        ],
        [
            "",
            "\\hat{\\bm{f}}"
        ],
        [
            "",
            "\\boldsymbol{x}"
        ],
        [
            "",
            "\\tilde{\\sigma}"
        ],
        [
            "",
            "\\boldsymbol{x}"
        ],
        [
            "",
            "\\sigma_l"
        ],
        [
            "",
            "\\boldsymbol{x}"
        ],
        [
            "",
            "\\vartheta_{il}"
        ],
        [
            "",
            "\\boldsymbol{x}"
        ],
        [
            "",
            "\\tilde{w}"
        ],
        [
            "",
            "\\boldsymbol{x}"
        ],
        [
            "",
            "\\mathcal{S}"
        ],
        [
            "",
            "\\sum_{l\\in{\\mathcal{S}}_i(\\boldsymbol{x})}"
        ],
        [
            "",
            "\\boldsymbol{x}"
        ],
        [
            "",
            "\\Gamma_i"
        ],
        [
            "",
            "\\boldsymbol{x}"
        ],
        [
            "",
            "\\sigma_l"
        ],
        [
            "",
            "\\boldsymbol{x}"
        ],
        [
            "",
            "\\sigma_{il}"
        ],
        [
            "",
            "\\sigma_{\\omega}"
        ],
        [
            "",
            "\\boldsymbol{x}"
        ],
        [
            "",
            "\\tilde{w}"
        ],
        [
            "",
            "\\boldsymbol{x}"
        ],
        [
            "",
            "\\mathcal{S}"
        ],
        [
            "",
            "\\sum_{l\\in\\mathcal{S}_i(\\boldsymbol{x})}"
        ],
        [
            "",
            "\\boldsymbol{x}"
        ],
        [
            "",
            "\\tilde{\\sigma}"
        ],
        [
            "",
            "\\boldsymbol{X}"
        ],
        [
            "",
            "\\boldsymbol{x}"
        ],
        [
            "",
            "\\boldsymbol{k}"
        ],
        [
            "",
            "\\boldsymbol{X}"
        ],
        [
            "",
            "\\boldsymbol{K}"
        ],
        [
            "",
            "\\bar{\\boldsymbol{K}}"
        ],
        [
            "",
            "\\boldsymbol{X}"
        ],
        [
            "",
            "\\boldsymbol{x}"
        ],
        [
            "",
            "\\boldsymbol{k}"
        ],
        [
            "",
            "\\bm{x}"
        ],
        [
            "",
            "\\eta_n"
        ],
        [
            "",
            "\\hat{\\eta}"
        ],
        [
            "",
            "\\bm{x}"
        ],
        [
            "",
            "\\eta_1"
        ],
        [
            "",
            "\\hat{\\eta}"
        ],
        [
            "",
            "\\ell_{\\kappa}"
        ],
        [
            "",
            "\\boldsymbol{x}"
        ],
        [
            "",
            "\\boldsymbol{x}"
        ],
        [
            "",
            "\\sigma_{\\kappa}"
        ],
        [
            "",
            "\\boldsymbol{x}"
        ],
        [
            "",
            "\\boldsymbol{x}"
        ],
        [
            "",
            "\\boldsymbol{x}"
        ],
        [
            "",
            "\\sigma_l"
        ],
        [
            "",
            "\\boldsymbol{x}"
        ],
        [
            "",
            "\\tilde{\\sigma}"
        ],
        [
            "",
            "\\boldsymbol{x}"
        ],
        [
            "",
            "\\sigma_{is}"
        ],
        [
            "",
            "\\sigma_{\\omega}"
        ],
        [
            "",
            "\\boldsymbol{x}"
        ],
        [
            "",
            "\\tilde{w}"
        ],
        [
            "",
            "\\boldsymbol{x}"
        ],
        [
            "",
            "\\mathcal{S}"
        ],
        [
            "",
            "\\sum_{l\\in{\\mathcal{S}}_i(\\boldsymbol{x})}"
        ],
        [
            "",
            "\\boldsymbol{x}"
        ],
        [
            "",
            "\\tilde{\\sigma}"
        ],
        [
            "",
            "\\boldsymbol{x}"
        ],
        [
            "",
            "\\sigma_s"
        ],
        [
            "",
            "\\boldsymbol{x}"
        ],
        [
            "",
            "\\sigma_{is}"
        ],
        [
            "",
            "\\sigma_{\\omega}"
        ],
        [
            "",
            "\\boldsymbol{x}"
        ],
        [
            "",
            "\\tilde{w}"
        ],
        [
            "",
            "\\boldsymbol{x}"
        ],
        [
            "",
            "\\mathcal{O}"
        ],
        [
            "",
            "\\sigma_{\\omega}"
        ],
        [
            "",
            "\\mathbb{I}"
        ],
        [
            "",
            "\\bar{\\mathbb{I}}"
        ],
        [
            "",
            "\\delta_n"
        ],
        [
            "",
            "\\delta_n"
        ],
        [
            "",
            "\\boldsymbol{x}"
        ],
        [
            "",
            "\\bm{e}"
        ],
        [
            "",
            "\\bm{x}"
        ],
        [
            "",
            "\\bm{x}"
        ],
        [
            "",
            "\\boldsymbol{x}"
        ],
        [
            "",
            "\\mathbb{I}"
        ],
        [
            "",
            "\\sum_{p \\in \\mathbb{I}_i(\\boldsymbol{x}(t_k))}"
        ],
        [
            "",
            "\\sigma_{\\omega}"
        ],
        [
            "",
            "\\bm{x}"
        ],
        [
            "",
            "\\mu_i"
        ],
        [
            "",
            "\\bm{\\mu}"
        ],
        [
            "",
            "\\boldsymbol{x}"
        ],
        [
            "",
            "\\varepsilon_i"
        ],
        [
            "",
            "\\delta_n"
        ],
        [
            "",
            "\\delta_{\\rho}"
        ],
        [
            "",
            "\\delta_n"
        ],
        [
            "",
            "\\mathbb{R}"
        ],
        [
            "",
            "\\bm{y}"
        ],
        [
            "",
            "\\boldsymbol{X}"
        ],
        [
            "",
            "\\boldsymbol{K}"
        ],
        [
            "",
            "\\bar{\\boldsymbol{K}}"
        ],
        [
            "",
            "\\sigma_{\\omega}"
        ],
        [
            "",
            "\\mathbb{R}"
        ],
        [
            "",
            "\\ell_{\\kappa}"
        ],
        [
            "",
            "\\mathbb{R}"
        ],
        [
            "",
            "\\sigma_{\\kappa}"
        ],
        [
            "",
            "\\mathbb{X}"
        ],
        [
            "",
            "\\boldsymbol{x}"
        ],
        [
            "",
            "\\boldsymbol{x}"
        ],
        [
            "",
            "\\mathbb{D}"
        ],
        [
            "",
            "\\varpi_{is}"
        ],
        [
            "",
            "\\bm{x}"
        ],
        [
            "",
            "\\bm{f}"
        ],
        [
            "",
            "\\bm{x}"
        ],
        [
            "",
            "\\mu_i"
        ],
        [
            "",
            "\\bm{\\mu}"
        ],
        [
            "",
            "\\tilde{\\bm{\\mu}}"
        ],
        [
            "",
            "\\mathcal{N}"
        ],
        [
            "",
            "\\bar{\\mathcal{N}}"
        ],
        [
            "",
            "\\mathbb{I}"
        ],
        [
            "",
            "\\boldsymbol{x}"
        ],
        [
            "",
            "\\varepsilon_{s}"
        ],
        [
            "",
            "\\boldsymbol{x}"
        ],
        [
            "",
            "\\mathbb{I}"
        ],
        [
            "",
            "\\boldsymbol{y}"
        ],
        [
            "",
            "\\boldsymbol{X}"
        ],
        [
            "",
            "\\boldsymbol{K}"
        ],
        [
            "",
            "\\bar{\\boldsymbol{K}}"
        ],
        [
            "",
            "\\boldsymbol{e}"
        ],
        [
            "",
            "\\bm{e}"
        ],
        [
            "",
            "\\boldsymbol{x}"
        ],
        [
            "",
            "\\boldsymbol{w}"
        ],
        [
            "",
            "\\tilde{\\boldsymbol{w}}"
        ],
        [
            "",
            "\\mathbb{I}"
        ],
        [
            "",
            "\\bar{\\mathbb{I}}"
        ],
        [
            "",
            "\\bm{y}"
        ],
        [
            "",
            "\\mathbb{I}"
        ],
        [
            "",
            "\\bar{\\mathbb{I}}"
        ],
        [
            "",
            "\\boldsymbol{X}"
        ],
        [
            "",
            "\\bm{f}"
        ],
        [
            "",
            "\\mathbb{I}"
        ],
        [
            "",
            "\\bar{\\mathbb{I}}"
        ],
        [
            "",
            "\\sigma_{\\omega}"
        ],
        [
            "",
            "\\mathcal{S}"
        ],
        [
            "",
            "\\boldsymbol{x}"
        ],
        [
            "",
            "\\sigma_l"
        ],
        [
            "",
            "\\boldsymbol{x}"
        ],
        [
            "",
            "\\vartheta_{il}"
        ],
        [
            "",
            "\\boldsymbol{x}"
        ],
        [
            "",
            "\\tilde{w}"
        ],
        [
            "",
            "\\boldsymbol{x}"
        ],
        [
            "",
            "\\mathcal{S}"
        ],
        [
            "",
            "\\sum_{l\\in\\mathcal{S}_i(\\boldsymbol{x})}"
        ],
        [
            "",
            "\\boldsymbol{x}"
        ],
        [
            "",
            "\\tilde{\\sigma}"
        ],
        [
            "",
            "\\mathbb{I}"
        ],
        [
            "",
            "\\sigma_{\\omega}"
        ],
        [
            "",
            "\\boldsymbol{x}"
        ],
        [
            "",
            "\\sigma_{i,\\rho}"
        ],
        [
            "",
            "\\boldsymbol{y}"
        ],
        [
            "",
            "\\boldsymbol{X}"
        ],
        [
            "",
            "\\boldsymbol{K}"
        ],
        [
            "",
            "\\bar{\\boldsymbol{K}}"
        ],
        [
            "",
            "\\boldsymbol{X}"
        ],
        [
            "",
            "\\boldsymbol{x}"
        ],
        [
            "",
            "\\boldsymbol{k}"
        ],
        [
            "",
            "\\mathbb{D}"
        ],
        [
            "",
            "\\boldsymbol{x}"
        ],
        [
            "",
            "\\mu_i"
        ],
        [
            "",
            "\\delta_x"
        ],
        [
            "",
            "\\boldsymbol{x}"
        ],
        [
            "",
            "\\bm{x}"
        ],
        [
            "",
            "\\bm{x}"
        ],
        [
            "",
            "\\bar{\\bm{x}}"
        ],
        [
            "",
            "\\bm{x}"
        ],
        [
            "",
            "\\mu_n"
        ],
        [
            "",
            "\\bm{\\mu}"
        ],
        [
            "",
            "\\tilde{\\bm{\\mu}}"
        ],
        [
            "",
            "\\bm{x}"
        ],
        [
            "",
            "\\mu_1"
        ],
        [
            "",
            "\\bm{\\mu}"
        ],
        [
            "",
            "\\tilde{\\bm{\\mu}}"
        ],
        [
            "",
            "\\bm{x}"
        ],
        [
            "",
            "\\bar{\\bm{x}}"
        ],
        [
            "",
            "\\bm{\\mu}"
        ],
        [
            "",
            "\\tilde{\\bm{\\mu}}"
        ],
        [
            "",
            "\\bm{x}"
        ],
        [
            "",
            "\\bm{f}"
        ],
        [
            "",
            "\\bm{x}"
        ],
        [
            "",
            "\\bm{f}"
        ],
        [
            "",
            "\\bm{x}"
        ],
        [
            "",
            "\\bar{\\bm{x}}"
        ],
        [
            "",
            "\\bm{f}"
        ],
        [
            "",
            "\\mathbb{X}"
        ],
        [
            "",
            "\\bm{x}"
        ],
        [
            "",
            "\\mu_i"
        ],
        [
            "",
            "\\tilde{\\mu}"
        ],
        [
            "",
            "\\bm{x}"
        ],
        [
            "",
            "\\mu_i"
        ],
        [
            "",
            "\\tilde{\\mu}"
        ],
        [
            "",
            "\\bm{x}"
        ],
        [
            "",
            "\\mu_i"
        ],
        [
            "",
            "\\bm{\\mu}"
        ],
        [
            "",
            "\\tilde{\\bm{\\mu}}"
        ],
        [
            "",
            "\\boldsymbol{v}"
        ],
        [
            "",
            "\\boldsymbol{v}"
        ],
        [
            "",
            "\\boldsymbol{\\psi}"
        ],
        [
            "",
            "\\boldsymbol{v}"
        ],
        [
            "",
            "\\boldsymbol{v}"
        ],
        [
            "",
            "\\psi_i"
        ],
        [
            "\\mathbb",
            "\\mathbb"
        ],
        [
            "",
            "\\mathbb{R}"
        ],
        [
            "",
            "\\psi_i"
        ],
        [
            "",
            "\\mathbb{N}"
        ],
        [
            "\\mathbb",
            "\\mathbb"
        ],
        [
            "",
            "\\mathbb{R}"
        ],
        [
            "",
            "\\boldsymbol{\\psi}"
        ],
        [
            "",
            "\\mathcal{N}"
        ],
        [
            "",
            "\\bar{\\mathcal{N}}"
        ],
        [
            "",
            "\\boldsymbol{x}"
        ],
        [
            "",
            "\\varepsilon_{is}"
        ],
        [
            "",
            "\\tilde{\\varepsilon}"
        ],
        [
            "",
            "\\boldsymbol{x}"
        ],
        [
            "",
            "\\varepsilon_{i}"
        ],
        [
            "",
            "\\boldsymbol{\\varepsilon}"
        ],
        [
            "",
            "\\tilde{\\boldsymbol{\\varepsilon}}"
        ],
        [
            "",
            "\\boldsymbol{x}"
        ],
        [
            "",
            "\\mathcal{S}"
        ],
        [
            "",
            "\\boldsymbol{x}"
        ],
        [
            "",
            "\\phi_{is}"
        ],
        [
            "",
            "\\boldsymbol{x}"
        ],
        [
            "",
            "\\phi_{i}"
        ],
        [
            "",
            "\\boldsymbol{\\phi}"
        ],
        [
            "",
            "\\boldsymbol{x}"
        ],
        [
            "",
            "\\mathcal{S}"
        ],
        [
            "",
            "\\boldsymbol{x}"
        ],
        [
            "",
            "\\tilde{w}"
        ],
        [
            "",
            "\\boldsymbol{x}"
        ],
        [
            "",
            "\\boldsymbol{w}"
        ],
        [
            "",
            "\\tilde{\\boldsymbol{w}}"
        ],
        [
            "\\argmin",
            "\\argmin"
        ],
        [
            "",
            "\\mathbb{I}"
        ],
        [
            "",
            "\\bar{\\mathbb{I}}"
        ],
        [
            "",
            "\\boldsymbol{x}"
        ],
        [
            "",
            "\\mu_i"
        ],
        [
            "",
            "\\bm{\\mu}"
        ],
        [
            "",
            "\\boldsymbol{x}"
        ],
        [
            "",
            "\\mu_i"
        ],
        [
            "",
            "\\bm{\\mu}"
        ],
        [
            "",
            "\\mathbb{I}"
        ],
        [
            "",
            "\\bar{\\mathbb{I}}"
        ],
        [
            "",
            "\\boldsymbol{X}"
        ],
        [
            "",
            "\\mu_i"
        ],
        [
            "",
            "\\bm{\\mu}"
        ],
        [
            "",
            "\\boldsymbol{x}"
        ],
        [
            "",
            "\\bm{x}"
        ],
        [
            "",
            "\\bm{x}"
        ],
        [
            "",
            "\\mathcal{O}"
        ],
        [
            "",
            "\\boldsymbol{x}"
        ],
        [
            "",
            "\\mathbb{I}"
        ],
        [
            "",
            "\\mathcal{O}"
        ],
        [
            "",
            "\\sigma_{\\omega}"
        ],
        [
            "",
            "\\mathbb{I}"
        ],
        [
            "",
            "\\bm{X}"
        ],
        [
            "",
            "\\bm{K}"
        ],
        [
            "",
            "\\mathbb{I}"
        ],
        [
            "",
            "\\bm{X}"
        ],
        [
            "",
            "\\bm{x}"
        ],
        [
            "",
            "\\bm{k}"
        ],
        [
            "",
            "\\bm{x}"
        ],
        [
            "",
            "\\sigma_{i,\\rho}"
        ],
        [
            "",
            "\\boldsymbol{e}"
        ],
        [
            "",
            "\\boldsymbol{X}"
        ],
        [
            "",
            "\\tilde{\\boldsymbol{X}}"
        ],
        [
            "",
            "\\boldsymbol{x}"
        ],
        [
            "",
            "\\boldsymbol{X}"
        ],
        [
            "",
            "\\boldsymbol{K}"
        ],
        [
            "",
            "\\boldsymbol{X}"
        ],
        [
            "",
            "\\boldsymbol{K}"
        ],
        [
            "",
            "\\boldsymbol{x}"
        ],
        [
            "",
            "\\sigma_{i}"
        ],
        [
            "",
            "\\boldsymbol{\\sigma}"
        ],
        [
            "",
            "\\varpi_{is}"
        ],
        [
            "",
            "\\boldsymbol{x}"
        ],
        [
            "",
            "\\tilde{w}"
        ],
        [
            "",
            "\\mathcal{S}"
        ],
        [
            "",
            "\\cup_{s\\in\\mathcal{S}_i}"
        ],
        [
            "",
            "\\Psi_{is}"
        ],
        [
            "",
            "\\boldsymbol{x}"
        ],
        [
            "",
            "\\beta_{\\delta}"
        ],
        [
            "",
            "\\boldsymbol{x}"
        ],
        [
            "",
            "\\sigma_i"
        ],
        [
            "",
            "\\beta_{\\delta}"
        ],
        [
            "",
            "\\bm{x}"
        ],
        [
            "",
            "\\bm{f}"
        ],
        [
            "",
            "\\boldsymbol{x}"
        ],
        [
            "",
            "\\mu_i"
        ],
        [
            "",
            "\\bm{\\mu}"
        ],
        [
            "",
            "\\boldsymbol{x}"
        ],
        [
            "",
            "\\mathbb{I}"
        ],
        [
            "",
            "\\bar{\\mathbb{I}}"
        ],
        [
            "",
            "\\boldsymbol{x}"
        ],
        [
            "",
            "\\bm{e}"
        ],
        [
            "",
            "\\bm{x}"
        ],
        [
            "",
            "\\bm{x}"
        ],
        [
            "",
            "\\boldsymbol{x}"
        ],
        [
            "",
            "\\mathbb{I}"
        ],
        [
            "",
            "\\sum_{p \\in \\mathbb{I}_i(\\boldsymbol{x}(t_k),\\rho)}"
        ],
        [
            "",
            "\\boldsymbol{x}"
        ],
        [
            "",
            "\\varepsilon_i"
        ],
        [
            "assumption",
            "\\end{assumption}"
        ],
        [
            "assumption",
            "\\begin{assumption}"
        ],
        [
            "",
            "\\bm{x}"
        ],
        [
            "",
            "\\bm{x}"
        ],
        [
            "",
            "\\boldsymbol{x}"
        ],
        [
            "",
            "\\mathbb{I}"
        ],
        [
            "\\CASELINE",
            "\\CASELINE{}"
        ],
        [
            "",
            "\\mathcal{N}"
        ],
        [
            "",
            "\\bar{\\mathcal{N}}"
        ],
        [
            "",
            "\\mathcal{O}"
        ],
        [
            "",
            "\\boldsymbol{x}"
        ],
        [
            "",
            "\\mu_i"
        ],
        [
            "",
            "\\Psi_{is}"
        ],
        [
            "",
            "\\mathcal{S}"
        ],
        [
            "",
            "\\mathcal{S}"
        ],
        [
            "",
            "\\boldsymbol{x}"
        ],
        [
            "",
            "\\sigma_{is}"
        ],
        [
            "",
            "\\boldsymbol{x}"
        ],
        [
            "",
            "\\sigma_{i}"
        ],
        [
            "",
            "\\boldsymbol{\\sigma}"
        ],
        [
            "",
            "\\varpi_{is}"
        ],
        [
            "",
            "\\tilde{w}"
        ],
        [
            "",
            "\\Psi_{is}"
        ],
        [
            "",
            "\\boldsymbol{x}"
        ],
        [
            "",
            "\\phi_{is}"
        ],
        [
            "",
            "\\mathcal{N}"
        ],
        [
            "",
            "\\bar{\\mathcal{N}}"
        ],
        [
            "",
            "\\bm{x}"
        ],
        [
            "",
            "\\eta_n"
        ],
        [
            "",
            "\\hat{\\eta}"
        ],
        [
            "",
            "\\bm{x}"
        ],
        [
            "",
            "\\eta_1"
        ],
        [
            "",
            "\\hat{\\eta}"
        ],
        [
            "",
            "\\bm{x}"
        ],
        [
            "",
            "\\eta_i"
        ],
        [
            "",
            "\\hat{\\eta}"
        ],
        [
            "",
            "\\sum_{i=1}"
        ],
        [
            "",
            "\\bm{x}"
        ],
        [
            "",
            "\\eta_i"
        ],
        [
            "",
            "\\bm{x}"
        ],
        [
            "",
            "\\bm{f}"
        ],
        [
            "",
            "\\bm{x}"
        ],
        [
            "",
            "\\mu_i"
        ],
        [
            "",
            "\\bm{\\mu}"
        ],
        [
            "",
            "\\mathcal{S}"
        ],
        [
            "",
            "\\bm{x}"
        ],
        [
            "",
            "\\mu_{i}"
        ],
        [
            "",
            "\\bm{\\mu}"
        ],
        [
            "",
            "\\tilde{\\bm{\\mu}}"
        ],
        [
            "",
            "\\bm{x}"
        ],
        [
            "",
            "\\mu_i"
        ],
        [
            "",
            "\\bm{\\mu}"
        ],
        [
            "",
            "\\boldsymbol{Y}"
        ],
        [
            "",
            "\\boldsymbol{X}"
        ],
        [
            "",
            "\\boldsymbol{x}"
        ],
        [
            "",
            "\\sigma_{\\varepsilon,i}"
        ],
        [
            "",
            "\\boldsymbol{x}"
        ],
        [
            "",
            "\\varepsilon_{i}"
        ],
        [
            "",
            "\\bar{\\varepsilon}"
        ],
        [
            "",
            "\\boldsymbol{x}"
        ],
        [
            "",
            "\\varepsilon_{s}"
        ],
        [
            "",
            "\\bm{x}"
        ],
        [
            "",
            "\\eta_i"
        ],
        [
            "",
            "\\tilde{\\eta}"
        ],
        [
            "",
            "\\bm{x}"
        ],
        [
            "",
            "\\eta_i"
        ],
        [
            "",
            "\\tilde{\\eta}"
        ],
        [
            "",
            "\\bm{x}"
        ],
        [
            "",
            "\\eta_i"
        ],
        [
            "",
            "\\tilde{\\eta}"
        ],
        [
            "",
            "\\delta_x"
        ],
        [
            "",
            "\\bm{y}"
        ],
        [
            "",
            "\\bm{I}"
        ],
        [
            "",
            "\\bm{X}"
        ],
        [
            "",
            "\\boldsymbol{K}"
        ],
        [
            "",
            "\\bar{\\boldsymbol{K}}"
        ],
        [
            "",
            "\\bm{X}"
        ],
        [
            "",
            "\\bm{K}"
        ],
        [
            "",
            "\\bm{e}"
        ],
        [
            "",
            "\\boldsymbol{x}"
        ],
        [
            "",
            "\\boldsymbol{y}"
        ],
        [
            "",
            "\\boldsymbol{f}"
        ],
        [
            "",
            "\\sigma_{\\omega}"
        ],
        [
            "",
            "\\mathbb{I}"
        ],
        [
            "",
            "\\mathbb{I}"
        ],
        [
            "",
            "\\mathbb{I}"
        ],
        [
            "",
            "\\bar{\\mathbb{I}}"
        ],
        [
            "",
            "\\beta_{\\delta}"
        ],
        [
            "",
            "\\mathbb{I}"
        ],
        [
            "",
            "\\bar{\\mathbb{I}}"
        ],
        [
            "",
            "\\boldsymbol{X}"
        ],
        [
            "",
            "\\bm{f}"
        ],
        [
            "",
            "\\mathbb{I}"
        ],
        [
            "",
            "\\bar{\\mathbb{I}}"
        ],
        [
            "",
            "\\boldsymbol{X}"
        ],
        [
            "",
            "\\mu_i"
        ],
        [
            "",
            "\\bm{\\mu}"
        ],
        [
            "",
            "\\mathbb{I}"
        ],
        [
            "",
            "\\bar{\\mathbb{I}}"
        ],
        [
            "",
            "\\boldsymbol{x}"
        ],
        [
            "",
            "\\bm{e}"
        ],
        [
            "",
            "\\boldsymbol{x}"
        ],
        [
            "",
            "\\bm{e}"
        ],
        [
            "",
            "\\boldsymbol{x}"
        ],
        [
            "",
            "\\sigma_{\\varepsilon,i}"
        ],
        [
            "",
            "\\boldsymbol{x}"
        ],
        [
            "",
            "\\sigma_{\\varepsilon,i}"
        ],
        [
            "",
            "\\boldsymbol{x}"
        ],
        [
            "",
            "\\varepsilon_s"
        ],
        [
            "",
            "\\boldsymbol{x}"
        ],
        [
            "",
            "\\varepsilon_i"
        ],
        [
            "",
            "\\bar{\\varepsilon}"
        ],
        [
            "",
            "\\boldsymbol{x}"
        ],
        [
            "",
            "\\mathbb{I}"
        ],
        [
            "",
            "\\bar{\\mathbb{I}}"
        ],
        [
            "",
            "\\bm{y}"
        ],
        [
            "",
            "\\mathbb{I}"
        ],
        [
            "",
            "\\bar{\\mathbb{I}}"
        ],
        [
            "",
            "\\boldsymbol{X}"
        ],
        [
            "",
            "\\bm{f}"
        ],
        [
            "",
            "\\sigma_{\\omega}"
        ],
        [
            "",
            "\\mathbb{I}"
        ],
        [
            "",
            "\\mathcal{N}"
        ],
        [
            "",
            "\\bar{\\mathcal{N}}"
        ],
        [
            "",
            "\\boldsymbol{x}"
        ],
        [
            "",
            "\\varepsilon_{s}"
        ],
        [
            "",
            "\\boldsymbol{x}"
        ],
        [
            "",
            "\\mu_i"
        ],
        [
            "",
            "\\boldsymbol{x}"
        ],
        [
            "",
            "\\mu_i"
        ],
        [
            "",
            "\\boldsymbol{x}"
        ],
        [
            "",
            "\\mu_i"
        ],
        [
            "",
            "\\boldsymbol{\\mu}"
        ],
        [
            "",
            "\\bm{x}"
        ],
        [
            "",
            "\\bm{f}"
        ],
        [
            "",
            "\\bm{x}"
        ],
        [
            "",
            "\\bm{f}"
        ],
        [
            "",
            "\\hat{\\bm{f}}"
        ],
        [
            "",
            "\\bm{x}"
        ],
        [
            "",
            "\\bm{f}"
        ],
        [
            "",
            "\\bm{x}"
        ],
        [
            "",
            "\\mu_i"
        ],
        [
            "",
            "\\bm{\\mu}"
        ],
        [
            "",
            "\\tilde{\\bm{\\mu}}"
        ],
        [
            "",
            "\\boldsymbol{X}"
        ],
        [
            "",
            "\\boldsymbol{x}"
        ],
        [
            "",
            "\\boldsymbol{k}"
        ],
        [
            "",
            "\\boldsymbol{x}"
        ],
        [
            "",
            "\\boldsymbol{k}"
        ],
        [
            "",
            "\\bar{\\boldsymbol{k}}"
        ],
        [
            "",
            "\\bm{x}"
        ],
        [
            "",
            "\\eta_i"
        ],
        [
            "",
            "\\boldsymbol{x}"
        ],
        [
            "",
            "\\boldsymbol{x}"
        ],
        [
            "",
            "\\mathcal{S}"
        ],
        [
            "",
            "\\sum_{s \\in \\mathcal{S}_i(\\boldsymbol{x}(t_k))}"
        ],
        [
            "",
            "\\bm{x}"
        ],
        [
            "",
            "\\eta_i"
        ],
        [
            "",
            "\\hat{\\eta}"
        ],
        [
            "",
            "\\nu_{\\text{Pow}}"
        ],
        [
            "",
            "\\bm{x}"
        ],
        [
            "",
            "\\sigma_{i,\\rho}"
        ],
        [
            "",
            "\\mathcal{O}"
        ],
        [
            "",
            "\\delta_x"
        ],
        [
            "",
            "\\mathbb{E}"
        ],
        [
            "",
            "\\boldsymbol{e}"
        ],
        [
            "",
            "\\boldsymbol{x}"
        ],
        [
            "",
            "\\sigma_{il}"
        ],
        [
            "",
            "\\vartheta_{il}"
        ],
        [
            "",
            "\\mathcal{S}"
        ],
        [
            "",
            "\\sum_{l \\in \\mathcal{S}_i}"
        ],
        [
            "",
            "\\boldsymbol{x}"
        ],
        [
            "",
            "\\sigma_{is}"
        ],
        [
            "",
            "\\vartheta_{is}"
        ],
        [
            "",
            "\\boldsymbol{x}"
        ],
        [
            "",
            "\\sigma_{i}"
        ],
        [
            "",
            "\\boldsymbol{\\sigma}"
        ],
        [
            "",
            "\\varpi_{is}"
        ],
        [
            "",
            "\\beta_{\\delta}"
        ],
        [
            "",
            "\\sigma_{\\omega}"
        ],
        [
            "",
            "\\mathbb{I}"
        ],
        [
            "",
            "\\bar{\\mathbb{I}}"
        ],
        [
            "",
            "\\delta_n"
        ],
        [
            "",
            "\\delta_n"
        ],
        [
            "",
            "\\mathbb{I}"
        ],
        [
            "",
            "\\bar{\\mathbb{I}}"
        ],
        [
            "",
            "\\boldsymbol{x}"
        ],
        [
            "",
            "\\boldsymbol{x}"
        ],
        [
            "",
            "\\bm{e}"
        ],
        [
            "",
            "\\boldsymbol{x}"
        ],
        [
            "",
            "\\varepsilon_i"
        ],
        [
            "",
            "\\boldsymbol{x}"
        ],
        [
            "",
            "\\boldsymbol{x}"
        ],
        [
            "",
            "\\bm{f}"
        ],
        [
            "",
            "\\mathbb{I}"
        ],
        [
            "",
            "\\mu_i"
        ],
        [
            "",
            "\\bm{\\mu}"
        ],
        [
            "",
            "\\bm{e}"
        ],
        [
            "",
            "\\bm{x}"
        ],
        [
            "",
            "\\mu_i"
        ],
        [
            "",
            "\\bm{x}"
        ],
        [
            "",
            "\\mu_i"
        ],
        [
            "",
            "\\mu_i"
        ],
        [
            "",
            "\\bm{\\mu}"
        ],
        [
            "",
            "\\mathcal{N}"
        ],
        [
            "",
            "\\bar{\\mathcal{N}}"
        ],
        [
            "",
            "\\boldsymbol{x}"
        ],
        [
            "",
            "\\varepsilon_{s}"
        ],
        [
            "",
            "\\boldsymbol{x}"
        ],
        [
            "",
            "\\varepsilon_i"
        ],
        [
            "",
            "\\bar{\\varepsilon}"
        ],
        [
            "",
            "\\bm{y}"
        ],
        [
            "",
            "\\bm{y}"
        ],
        [
            "",
            "\\boldsymbol{X}"
        ],
        [
            "",
            "\\boldsymbol{K}"
        ],
        [
            "",
            "\\bar{\\boldsymbol{K}}"
        ],
        [
            "",
            "\\mathbb{D}"
        ],
        [
            "",
            "\\boldsymbol{x}"
        ],
        [
            "",
            "\\sigma_i"
        ],
        [
            "",
            "\\bm{x}"
        ],
        [
            "",
            "\\bm{f}"
        ],
        [
            "",
            "\\boldsymbol{x}"
        ],
        [
            "",
            "\\mu_i"
        ],
        [
            "",
            "\\bm{\\mu}"
        ],
        [
            "",
            "\\beta_{\\delta}"
        ],
        [
            "",
            "\\boldsymbol{x}"
        ],
        [
            "",
            "\\Gamma_i"
        ],
        [
            "",
            "\\boldsymbol{x}"
        ],
        [
            "",
            "\\tilde{\\sigma}"
        ],
        [
            "",
            "\\boldsymbol{x}"
        ],
        [
            "",
            "\\sigma_s"
        ],
        [
            "",
            "\\boldsymbol{x}"
        ],
        [
            "",
            "\\vartheta_{is}"
        ],
        [
            "",
            "\\boldsymbol{x}"
        ],
        [
            "",
            "\\tilde{w}"
        ],
        [
            "",
            "\\boldsymbol{x}"
        ],
        [
            "",
            "\\mathbb{N}"
        ],
        [
            "",
            "\\mathbb{N}"
        ],
        [
            "",
            "\\mathbb{I}"
        ],
        [
            "",
            "\\bar{\\mathbb{I}}"
        ],
        [
            "",
            "\\bm{x}"
        ],
        [
            "",
            "\\bm{f}"
        ],
        [
            "",
            "\\bm{x}"
        ],
        [
            "",
            "\\bm{f}"
        ],
        [
            "",
            "\\mathbb{I}"
        ],
        [
            "",
            "\\bar{\\mathbb{I}}"
        ],
        [
            "",
            "\\boldsymbol{X}"
        ],
        [
            "",
            "\\bm{f}"
        ],
        [
            "",
            "\\delta_n"
        ],
        [
            "",
            "\\mathbb{I}"
        ],
        [
            "",
            "\\bar{\\mathbb{I}}"
        ],
        [
            "",
            "\\mathbb{I}"
        ],
        [
            "",
            "\\bar{\\mathbb{I}}"
        ],
        [
            "",
            "\\bm{y}"
        ],
        [
            "",
            "\\mathbb{I}"
        ],
        [
            "",
            "\\bar{\\mathbb{I}}"
        ],
        [
            "",
            "\\boldsymbol{X}"
        ],
        [
            "",
            "\\bm{f}"
        ],
        [
            "",
            "\\sigma_{\\omega}"
        ],
        [
            "",
            "\\sigma_{\\omega}"
        ],
        [
            "",
            "\\mathbb{I}"
        ],
        [
            "",
            "\\bar{\\mathbb{I}}"
        ],
        [
            "",
            "\\mathbb{I}"
        ],
        [
            "",
            "\\bar{\\mathbb{I}}"
        ],
        [
            "",
            "\\bm{y}"
        ],
        [
            "",
            "\\mathbb{I}"
        ],
        [
            "",
            "\\bar{\\mathbb{I}}"
        ],
        [
            "",
            "\\boldsymbol{X}"
        ],
        [
            "",
            "\\bm{f}"
        ],
        [
            "",
            "\\mathbb{I}"
        ],
        [
            "",
            "\\bar{\\mathbb{I}}"
        ],
        [
            "",
            "\\delta_{\\rho}"
        ],
        [
            "",
            "\\boldsymbol{x}"
        ],
        [
            "",
            "\\boldsymbol{x}"
        ],
        [
            "",
            "\\mathbb{S}"
        ],
        [
            "",
            "\\sum_{s \\in \\mathbb{S}_i(\\boldsymbol{x})}"
        ],
        [
            "",
            "\\delta_x"
        ],
        [
            "",
            "\\bm{x}"
        ],
        [
            "",
            "\\sigma_{i}"
        ],
        [
            "",
            "\\beta_{\\delta}"
        ],
        [
            "",
            "\\bm{x}"
        ],
        [
            "",
            "\\bm{f}"
        ],
        [
            "",
            "\\bm{x}"
        ],
        [
            "",
            "\\mu_i"
        ],
        [
            "",
            "\\bm{\\mu}"
        ],
        [
            "",
            "\\bm{x}"
        ],
        [
            "",
            "\\eta_i"
        ],
        [
            "",
            "\\tilde{\\eta}"
        ],
        [
            "",
            "\\bm{x}"
        ],
        [
            "",
            "\\bm{f}"
        ],
        [
            "",
            "\\bm{x}"
        ],
        [
            "",
            "\\mu_i"
        ],
        [
            "",
            "\\bm{\\mu}"
        ],
        [
            "",
            "\\tilde{\\bm{\\mu}}"
        ],
        [
            "",
            "\\mathbb{D}"
        ],
        [
            "",
            "\\mathcal{N}"
        ],
        [
            "",
            "\\epsilon_0"
        ],
        [
            "",
            "\\boldsymbol{I}"
        ],
        [
            "",
            "\\sigma_{\\omega}"
        ],
        [
            "",
            "\\boldsymbol{X}"
        ],
        [
            "",
            "\\boldsymbol{K}"
        ],
        [
            "",
            "\\boldsymbol{X}"
        ],
        [
            "",
            "\\boldsymbol{K}"
        ],
        [
            "",
            "\\bar{\\boldsymbol{K}}"
        ],
        [
            "lemma",
            "\\end{lemma}"
        ],
        [
            "lemma",
            "\\begin{lemma}"
        ],
        [
            "",
            "\\sigma_{\\omega}"
        ],
        [
            "",
            "\\boldsymbol{x}"
        ],
        [
            "",
            "\\phi_{is}"
        ],
        [
            "",
            "\\delta_{\\rho}"
        ],
        [
            "",
            "\\mathbb{X}"
        ],
        [
            "",
            "\\bar{x}"
        ],
        [
            "",
            "\\delta_n"
        ],
        [
            "",
            "\\mathbb{R}"
        ],
        [
            "",
            "\\boldsymbol{y}"
        ],
        [
            "",
            "\\boldsymbol{Y}"
        ],
        [
            "",
            "\\boldsymbol{Y}"
        ],
        [
            "",
            "\\mathrm{diag}"
        ],
        [
            "",
            "\\mathcal{V}"
        ],
        [
            "",
            "\\boldsymbol{x}"
        ],
        [
            "",
            "\\mu_s"
        ],
        [
            "",
            "\\tilde{\\mu}"
        ],
        [
            "",
            "\\boldsymbol{x}"
        ],
        [
            "",
            "\\boldsymbol{x}"
        ],
        [
            "",
            "\\mathcal{S}"
        ],
        [
            "",
            "\\sum_{s\\in \\mathcal{S}_i(\\boldsymbol{x})}"
        ],
        [
            "",
            "\\boldsymbol{x}"
        ],
        [
            "",
            "\\hat{f}"
        ],
        [
            "",
            "\\boldsymbol{x}"
        ],
        [
            "",
            "\\phi_{is}"
        ],
        [
            "",
            "\\boldsymbol{x}"
        ],
        [
            "",
            "\\mathcal{S}"
        ],
        [
            "",
            "\\delta_x"
        ],
        [
            "",
            "\\mathbb{R}"
        ],
        [
            "",
            "\\mathbb{I}"
        ],
        [
            "",
            "\\bar{\\mathbb{I}}"
        ],
        [
            "",
            "\\boldsymbol{X}"
        ],
        [
            "",
            "\\bm{f}"
        ],
        [
            "",
            "\\mathbb{I}"
        ],
        [
            "",
            "\\bar{\\mathbb{I}}"
        ],
        [
            "",
            "\\boldsymbol{X}"
        ],
        [
            "",
            "\\mu_i"
        ],
        [
            "",
            "\\bm{\\mu}"
        ],
        [
            "",
            "\\vartheta_{il}"
        ],
        [
            "",
            "\\mathbb{R}"
        ],
        [
            "",
            "\\gamma_{is}"
        ],
        [
            "",
            "\\boldsymbol{x}"
        ],
        [
            "",
            "\\varepsilon_i"
        ],
        [
            "",
            "\\boldsymbol{x}"
        ],
        [
            "",
            "\\bm{e}"
        ],
        [
            "",
            "\\bm{x}"
        ],
        [
            "",
            "\\bm{x}"
        ],
        [
            "",
            "\\mathbb{I}"
        ],
        [
            "",
            "\\sum_{p \\in \\mathbb{I}_i(t_k,\\rho)}"
        ],
        [
            "",
            "\\sigma_{\\omega}"
        ],
        [
            "",
            "\\sigma_{\\omega}"
        ],
        [
            "",
            "\\mathbb{I}"
        ],
        [
            "",
            "\\mathbb{I}"
        ],
        [
            "",
            "\\beta_{\\delta}"
        ],
        [
            "",
            "\\nu_{\\text{Ex}}"
        ],
        [
            "",
            "\\mathbb{E}"
        ],
        [
            "",
            "\\mathbb{D}"
        ],
        [
            "",
            "\\sigma_{\\text{prior}}"
        ],
        [
            "",
            "\\vartheta_{il}"
        ],
        [
            "",
            "\\mathcal{S}"
        ],
        [
            "",
            "\\sum_{l\\in\\mathcal{S}_i}"
        ],
        [
            "",
            "\\boldsymbol{x}"
        ],
        [
            "",
            "\\sigma_{il}"
        ],
        [
            "",
            "\\mathcal{S}"
        ],
        [
            "",
            "\\sum_{l \\in \\mathcal{S}_i}"
        ],
        [
            "",
            "\\boldsymbol{x}"
        ],
        [
            "",
            "\\sigma_{is}"
        ],
        [
            "",
            "\\vartheta_{is}"
        ],
        [
            "",
            "\\boldsymbol{x}"
        ],
        [
            "",
            "\\sigma_{i}"
        ],
        [
            "",
            "\\boldsymbol{\\sigma}"
        ],
        [
            "",
            "\\varpi_{is}"
        ],
        [
            "",
            "\\boldsymbol{Y}"
        ],
        [
            "",
            "\\tilde{\\boldsymbol{Y}}"
        ],
        [
            "",
            "\\boldsymbol{X}"
        ],
        [
            "",
            "\\tilde{\\boldsymbol{X}}"
        ],
        [
            "",
            "\\bm{x}"
        ],
        [
            "",
            "\\bm{f}"
        ],
        [
            "",
            "\\bm{x}"
        ],
        [
            "",
            "\\mu_i"
        ],
        [
            "",
            "\\bm{\\mu}"
        ],
        [
            "",
            "\\tilde{\\bm{\\mu}}"
        ],
        [
            "",
            "\\boldsymbol{x}"
        ],
        [
            "",
            "\\boldsymbol{x}"
        ],
        [
            "",
            "\\mathbb{S}"
        ],
        [
            "",
            "\\sum_{s \\in \\mathbb{S}_i(\\boldsymbol{x}(t_k))}"
        ],
        [
            "",
            "\\boldsymbol{x}"
        ],
        [
            "",
            "\\boldsymbol{k}"
        ],
        [
            "",
            "\\bar{\\boldsymbol{k}}"
        ],
        [
            "",
            "\\mathcal{N}"
        ],
        [
            "",
            "\\bar{\\mathcal{N}}"
        ],
        [
            "",
            "\\boldsymbol{x}"
        ],
        [
            "",
            "\\varepsilon_{s}"
        ],
        [
            "",
            "\\boldsymbol{x}"
        ],
        [
            "",
            "\\sigma_{\\varepsilon,i}"
        ],
        [
            "",
            "\\bar{x}"
        ],
        [
            "",
            "\\sum_{j=1}"
        ],
        [
            "",
            "\\beta_{\\delta}"
        ],
        [
            "",
            "\\boldsymbol{X}"
        ],
        [
            "",
            "\\boldsymbol{x}"
        ],
        [
            "",
            "\\boldsymbol{x}"
        ],
        [
            "",
            "\\mu_i"
        ],
        [
            "",
            "\\boldsymbol{x}"
        ],
        [
            "",
            "\\bm{x}"
        ],
        [
            "",
            "\\bm{f}"
        ],
        [
            "",
            "\\bm{x}"
        ],
        [
            "",
            "\\bm{f}"
        ],
        [
            "",
            "\\hat{\\bm{f}}"
        ],
        [
            "",
            "\\omega_{i,k}"
        ],
        [
            "",
            "\\boldsymbol{x}"
        ],
        [
            "",
            "\\mathbb{N}"
        ],
        [
            "",
            "\\mathcal{V}"
        ],
        [
            "",
            "\\boldsymbol{y}"
        ],
        [
            "",
            "\\boldsymbol{x}"
        ],
        [
            "",
            "\\boldsymbol{x}"
        ],
        [
            "",
            "\\boldsymbol{k}"
        ],
        [
            "",
            "\\bar{\\boldsymbol{k}}"
        ],
        [
            "",
            "\\boldsymbol{X}"
        ],
        [
            "",
            "\\boldsymbol{K}"
        ],
        [
            "theorem",
            "\\end{theorem}"
        ],
        [
            "theorem",
            "\\begin{theorem}"
        ],
        [
            "",
            "\\mathbb{R}"
        ],
        [
            "",
            "\\mathbb{R}"
        ],
        [
            "",
            "\\mathbb{R}"
        ],
        [
            "",
            "\\boldsymbol{x}"
        ],
        [
            "",
            "\\boldsymbol{X}"
        ],
        [
            "",
            "\\boldsymbol{X}"
        ],
        [
            "",
            "\\mathbb{I}"
        ],
        [
            "",
            "\\bar{\\mathbb{I}}"
        ],
        [
            "",
            "\\bm{y}"
        ],
        [
            "",
            "\\bm{y}"
        ],
        [
            "",
            "\\mathbb{I}"
        ],
        [
            "",
            "\\bar{\\mathbb{I}}"
        ],
        [
            "",
            "\\bm{y}"
        ],
        [
            "",
            "\\boldsymbol{Y}"
        ],
        [
            "",
            "\\tilde{\\boldsymbol{Y}}"
        ],
        [
            "",
            "\\boldsymbol{Y}"
        ],
        [
            "",
            "\\boldsymbol{Y}"
        ],
        [
            "",
            "\\boldsymbol{X}"
        ],
        [
            "",
            "\\tilde{\\boldsymbol{X}}"
        ],
        [
            "",
            "\\boldsymbol{X}"
        ],
        [
            "",
            "\\boldsymbol{X}"
        ],
        [
            "",
            "\\bm{x}"
        ],
        [
            "",
            "\\eta_i"
        ],
        [
            "",
            "\\bm{x}"
        ],
        [
            "",
            "\\mu_{i}"
        ],
        [
            "",
            "\\boldsymbol{\\mu}"
        ],
        [
            "",
            "\\tilde{\\boldsymbol{\\mu}}"
        ],
        [
            "",
            "\\boldsymbol{x}"
        ],
        [
            "",
            "\\varepsilon_i"
        ],
        [
            "",
            "\\bm{x}"
        ],
        [
            "",
            "\\eta_i"
        ],
        [
            "",
            "\\tilde{\\eta}"
        ],
        [
            "",
            "\\delta_x"
        ],
        [
            "",
            "\\boldsymbol{x}"
        ],
        [
            "",
            "\\boldsymbol{x}"
        ],
        [
            "",
            "\\phi_{is}"
        ],
        [
            "\\ENDCASE",
            "\\ENDCASE"
        ],
        [
            "",
            "\\sigma_{\\omega}"
        ],
        [
            "",
            "\\epsilon_0"
        ],
        [
            "",
            "\\bm{x}"
        ],
        [
            "",
            "\\sigma_{i,\\rho}"
        ],
        [
            "",
            "\\mathbb{I}"
        ],
        [
            "\\red",
            "\\red{}"
        ],
        [
            "",
            "\\bm{x}"
        ],
        [
            "",
            "\\bm{x}"
        ],
        [
            "",
            "\\mathbb{I}"
        ],
        [
            "",
            "\\bm{x}"
        ],
        [
            "",
            "\\sigma_{i,\\rho}"
        ],
        [
            "",
            "\\bm{x}"
        ],
        [
            "",
            "\\sigma_{i,\\rho}"
        ],
        [
            "",
            "\\bm{x}"
        ],
        [
            "",
            "\\sigma_{i}"
        ],
        [
            "",
            "\\sigma_{\\omega}"
        ],
        [
            "",
            "\\mathcal{N}"
        ],
        [
            "",
            "\\bar{\\mathcal{N}}"
        ],
        [
            "",
            "\\mathcal{O}"
        ],
        [
            "",
            "\\boldsymbol{x}"
        ],
        [
            "",
            "\\mathbb{I}"
        ],
        [
            "",
            "\\boldsymbol{x}"
        ],
        [
            "",
            "\\mathcal{S}"
        ],
        [
            "",
            "\\mathcal{O}"
        ],
        [
            "",
            "\\boldsymbol{x}"
        ],
        [
            "",
            "\\sigma_i"
        ],
        [
            "",
            "\\mathbb{D}"
        ],
        [
            "",
            "\\boldsymbol{x}"
        ],
        [
            "",
            "\\sigma_i"
        ],
        [
            "",
            "\\boldsymbol{x}"
        ],
        [
            "",
            "\\mu_i"
        ],
        [
            "",
            "\\mathbb{D}"
        ],
        [
            "",
            "\\boldsymbol{x}"
        ],
        [
            "",
            "\\mu_i"
        ],
        [
            "",
            "\\mathbb{N}"
        ],
        [
            "",
            "\\bar{N}"
        ],
        [
            "",
            "\\boldsymbol{Y}"
        ],
        [
            "",
            "\\tilde{\\boldsymbol{Y}}"
        ],
        [
            "",
            "\\bm{x}"
        ],
        [
            "",
            "\\bm{f}"
        ],
        [
            "",
            "\\bm{x}"
        ],
        [
            "",
            "\\bm{f}"
        ],
        [
            "",
            "\\hat{\\bm{f}}"
        ],
        [
            "",
            "\\sum_{i=1}"
        ],
        [
            "",
            "\\boldsymbol{x}"
        ],
        [
            "",
            "\\varepsilon_i"
        ],
        [
            "",
            "\\mathbb{D}"
        ],
        [
            "",
            "\\bm{x}"
        ],
        [
            "",
            "\\mu_{i,\\rho}"
        ],
        [
            "",
            "\\bm{\\mu}"
        ],
        [
            "",
            "\\boldsymbol{x}"
        ],
        [
            "",
            "\\varepsilon_i"
        ],
        [
            "",
            "\\bm{x}"
        ],
        [
            "",
            "\\mu_{i}"
        ],
        [
            "",
            "\\bm{\\mu}"
        ],
        [
            "",
            "\\tilde{\\bm{\\mu}}"
        ],
        [
            "",
            "\\bm{x}"
        ],
        [
            "",
            "\\mu_{i}"
        ],
        [
            "",
            "\\bm{\\mu}"
        ],
        [
            "",
            "\\tilde{\\bm{\\mu}}"
        ],
        [
            "",
            "\\bm{x}"
        ],
        [
            "",
            "\\mu_i"
        ],
        [
            "",
            "\\bm{\\mu}"
        ],
        [
            "",
            "\\boldsymbol{x}"
        ],
        [
            "",
            "\\mathcal{S}"
        ],
        [
            "",
            "\\mathcal{N}"
        ],
        [
            "",
            "\\bar{\\mathcal{N}}"
        ],
        [
            "",
            "\\boldsymbol{x}"
        ],
        [
            "",
            "\\mathcal{S}"
        ],
        [
            "",
            "\\boldsymbol{x}"
        ],
        [
            "",
            "\\boldsymbol{x}"
        ],
        [
            "",
            "\\boldsymbol{x}"
        ],
        [
            "",
            "\\boldsymbol{x}"
        ],
        [
            "",
            "\\boldsymbol{x}"
        ],
        [
            "",
            "\\boldsymbol{x}"
        ],
        [
            "",
            "\\mathcal{V}"
        ],
        [
            "",
            "\\boldsymbol{x}"
        ],
        [
            "",
            "\\varepsilon_{i}"
        ],
        [
            "",
            "\\boldsymbol{\\varepsilon}"
        ],
        [
            "",
            "\\tilde{\\boldsymbol{\\varepsilon}}"
        ],
        [
            "",
            "\\boldsymbol{x}"
        ],
        [
            "",
            "\\phi_{i}"
        ],
        [
            "",
            "\\boldsymbol{\\phi}"
        ],
        [
            "",
            "\\boldsymbol{\\psi}"
        ],
        [
            "\\blue",
            "\\blue{}"
        ],
        [
            "",
            "\\boldsymbol{X}"
        ],
        [
            "",
            "\\boldsymbol{x}"
        ],
        [
            "",
            "\\boldsymbol{k}"
        ],
        [
            "",
            "\\boldsymbol{X}"
        ],
        [
            "",
            "\\boldsymbol{x}"
        ],
        [
            "",
            "\\boldsymbol{k}"
        ],
        [
            "",
            "\\boldsymbol{f}"
        ],
        [
            "",
            "\\boldsymbol{f}"
        ],
        [
            "",
            "\\hat{\\boldsymbol{f}}"
        ],
        [
            "",
            "\\bm{x}"
        ],
        [
            "",
            "\\eta_i"
        ],
        [
            "",
            "\\hat{\\eta}"
        ],
        [
            "",
            "\\bm{x}"
        ],
        [
            "",
            "\\eta_i"
        ],
        [
            "",
            "\\tilde{\\eta}"
        ],
        [
            "",
            "\\boldsymbol{x}"
        ],
        [
            "",
            "\\boldsymbol{x}"
        ],
        [
            "",
            "\\mathbb{S}"
        ],
        [
            "",
            "\\sum_{s \\in \\mathbb{S}_i(\\boldsymbol{x}(t_k))}"
        ],
        [
            "",
            "\\boldsymbol{x}"
        ],
        [
            "",
            "\\boldsymbol{k}"
        ],
        [
            "",
            "\\bar{\\boldsymbol{k}}"
        ],
        [
            "",
            "\\boldsymbol{X}"
        ],
        [
            "",
            "\\boldsymbol{x}"
        ],
        [
            "",
            "\\boldsymbol{k}"
        ],
        [
            "corollary",
            "\\end{corollary}"
        ],
        [
            "corollary",
            "\\begin{corollary}"
        ],
        [
            "",
            "\\boldsymbol{x}"
        ],
        [
            "",
            "\\mu_s"
        ],
        [
            "",
            "\\gamma_{is}"
        ],
        [
            "",
            "\\mathbb{E}"
        ],
        [
            "\\SWITCH",
            "\\SWITCH{}"
        ],
        [
            "",
            "\\bar{\\lambda}"
        ],
        [
            "example",
            "\\end{example}"
        ],
        [
            "example",
            "\\begin{example}"
        ],
        [
            "",
            "\\bm{x}"
        ],
        [
            "",
            "\\bar{\\bm{x}}"
        ],
        [
            "",
            "\\hat{\\eta}"
        ],
        [
            "",
            "\\bm{x}"
        ],
        [
            "",
            "\\bar{\\bm{x}}"
        ],
        [
            "",
            "\\bm{f}"
        ],
        [
            "",
            "\\bm{x}"
        ],
        [
            "",
            "\\bar{\\bm{x}}"
        ],
        [
            "",
            "\\bm{f}"
        ],
        [
            "",
            "\\hat{\\bm{f}}"
        ],
        [
            "",
            "\\boldsymbol{x}"
        ],
        [
            "",
            "\\mathcal{S}"
        ],
        [
            "",
            "\\sum_{l \\in \\mathcal{S}_i}"
        ],
        [
            "",
            "\\mathcal{S}"
        ],
        [
            "",
            "\\cup_{s \\in \\mathcal{S}_i}"
        ],
        [
            "",
            "\\Psi_{is}"
        ],
        [
            "",
            "\\boldsymbol{x}"
        ],
        [
            "",
            "\\varepsilon_i"
        ],
        [
            "",
            "\\bm{e}"
        ],
        [
            "",
            "\\boldsymbol{X}"
        ],
        [
            "",
            "\\bm{x}"
        ],
        [
            "",
            "\\boldsymbol{k}"
        ],
        [
            "",
            "\\sigma_{\\omega}"
        ],
        [
            "",
            "\\bm{x}"
        ],
        [
            "",
            "\\mu_i"
        ],
        [
            "",
            "\\sigma_{\\omega}"
        ],
        [
            "",
            "\\mathbb{I}"
        ],
        [
            "",
            "\\bar{\\mathbb{I}}"
        ],
        [
            "",
            "\\bm{x}"
        ],
        [
            "",
            "\\mu_{i}"
        ],
        [
            "",
            "\\bm{\\mu}"
        ],
        [
            "",
            "\\tilde{\\bm{\\mu}}"
        ],
        [
            "",
            "\\bm{x}"
        ],
        [
            "",
            "\\mu_i"
        ],
        [
            "",
            "\\bm{\\mu}"
        ],
        [
            "",
            "\\boldsymbol{y}"
        ],
        [
            "",
            "\\boldsymbol{x}"
        ],
        [
            "",
            "\\boldsymbol{x}"
        ],
        [
            "",
            "\\boldsymbol{x}"
        ],
        [
            "",
            "\\boldsymbol{x}"
        ],
        [
            "",
            "\\boldsymbol{X}"
        ],
        [
            "",
            "\\boldsymbol{x}"
        ],
        [
            "",
            "\\boldsymbol{k}"
        ],
        [
            "",
            "\\boldsymbol{x}"
        ],
        [
            "",
            "\\boldsymbol{x}"
        ],
        [
            "",
            "\\boldsymbol{X}"
        ],
        [
            "",
            "\\boldsymbol{K}"
        ],
        [
            "",
            "\\boldsymbol{x}"
        ],
        [
            "",
            "\\phi_{is}"
        ],
        [
            "",
            "\\boldsymbol{x}"
        ],
        [
            "",
            "\\boldsymbol{X}"
        ],
        [
            "",
            "\\boldsymbol{x}"
        ],
        [
            "",
            "\\boldsymbol{x}"
        ],
        [
            "",
            "\\boldsymbol{e}"
        ],
        [
            "",
            "\\boldsymbol{e}"
        ],
        [
            "",
            "\\mathbb{E}"
        ],
        [
            "",
            "\\bm{x}"
        ],
        [
            "",
            "\\bm{f}"
        ],
        [
            "",
            "\\bm{x}"
        ],
        [
            "",
            "\\mu_{i}"
        ],
        [
            "",
            "\\bm{\\mu}"
        ],
        [
            "",
            "\\bm{x}"
        ],
        [
            "",
            "\\mu_{i}"
        ],
        [
            "",
            "\\bm{\\mu}"
        ],
        [
            "",
            "\\bm{x}"
        ],
        [
            "",
            "\\mu_i"
        ],
        [
            "",
            "\\bm{\\mu}"
        ],
        [
            "",
            "\\tilde{\\bm{\\mu}}"
        ],
        [
            "",
            "\\boldsymbol{x}"
        ],
        [
            "",
            "\\sigma_{is}"
        ],
        [
            "",
            "\\sigma_{\\omega}"
        ],
        [
            "",
            "\\boldsymbol{x}"
        ],
        [
            "",
            "\\vartheta_{is}"
        ],
        [
            "",
            "\\boldsymbol{x}"
        ],
        [
            "",
            "\\tilde{{w}}"
        ],
        [
            "",
            "\\boldsymbol{x}"
        ],
        [
            "",
            "\\delta_x"
        ],
        [
            "",
            "\\mathcal{N}"
        ],
        [
            "",
            "\\mathcal{N}"
        ],
        [
            "",
            "\\bar{\\mathcal{N}}"
        ],
        [
            "",
            "\\mathcal{E}"
        ],
        [
            "",
            "\\mathcal{V}"
        ],
        [
            "",
            "\\mathcal{N}"
        ],
        [
            "",
            "\\mathcal{E}"
        ],
        [
            "",
            "\\mathcal{V}"
        ],
        [
            "",
            "\\mathcal{V}"
        ],
        [
            "",
            "\\mathcal{E}"
        ],
        [
            "",
            "\\mathcal{V}"
        ],
        [
            "",
            "\\mathcal{E}"
        ],
        [
            "",
            "\\mathcal{V}"
        ],
        [
            "",
            "\\mathcal{G}"
        ],
        [
            "",
            "\\mathbb{N}"
        ],
        [
            "",
            "\\tilde{w}"
        ],
        [
            "",
            "\\nu_{\\text{Lin}}"
        ],
        [
            "",
            "\\mathbb{X}"
        ],
        [
            "",
            "\\boldsymbol{x}"
        ],
        [
            "",
            "\\mathcal{V}"
        ],
        [
            "",
            "\\mathbb{D}"
        ],
        [
            "",
            "\\boldsymbol{f}"
        ],
        [
            "",
            "\\bar{N}"
        ],
        [
            "",
            "\\sigma_{\\omega}"
        ],
        [
            "",
            "\\boldsymbol{x}"
        ],
        [
            "",
            "\\vartheta_{is}"
        ],
        [
            "",
            "\\boldsymbol{x}"
        ],
        [
            "",
            "\\tilde{w}"
        ],
        [
            "",
            "\\boldsymbol{x}"
        ],
        [
            "",
            "\\mathcal{S}"
        ],
        [
            "",
            "\\sum_{l\\in\\mathcal{S}_i(\\boldsymbol{x})}"
        ],
        [
            "",
            "\\bm{x}"
        ],
        [
            "",
            "\\bm{x}"
        ],
        [
            "",
            "\\boldsymbol{x}"
        ],
        [
            "",
            "\\sum_{p=1}"
        ],
        [
            "",
            "\\sigma_{\\omega}"
        ],
        [
            "",
            "\\bm{x}"
        ],
        [
            "",
            "\\mu_i"
        ],
        [
            "",
            "\\boldsymbol{Y}"
        ],
        [
            "",
            "\\boldsymbol{X}"
        ],
        [
            "",
            "\\boldsymbol{x}"
        ],
        [
            "",
            "\\hat{f}"
        ],
        [
            "\\commentZW",
            "\\commentZW{}{}"
        ],
        [
            "",
            "\\boldsymbol{x}"
        ],
        [
            "",
            "\\varepsilon_i"
        ],
        [
            "",
            "\\bar{\\varepsilon}"
        ],
        [
            "",
            "\\boldsymbol{x}"
        ],
        [
            "",
            "\\varepsilon_{s}"
        ],
        [
            "",
            "\\boldsymbol{y}"
        ],
        [
            "",
            "\\boldsymbol{y}"
        ],
        [
            "",
            "\\boldsymbol{y}"
        ],
        [
            "",
            "\\boldsymbol{Y}"
        ],
        [
            "",
            "\\boldsymbol{Y}"
        ],
        [
            "",
            "\\boldsymbol{x}"
        ],
        [
            "",
            "\\boldsymbol{x}"
        ],
        [
            "",
            "\\boldsymbol{x}"
        ],
        [
            "",
            "\\boldsymbol{X}"
        ],
        [
            "",
            "\\boldsymbol{X}"
        ],
        [
            "",
            "\\mathcal{V}"
        ],
        [
            "",
            "\\boldsymbol{y}"
        ],
        [
            "",
            "\\boldsymbol{x}"
        ],
        [
            "",
            "\\mathbb{N}"
        ],
        [
            "",
            "\\boldsymbol{Y}"
        ],
        [
            "",
            "\\boldsymbol{X}"
        ],
        [
            "",
            "\\mathbb{D}"
        ],
        [
            "",
            "\\mathbb{N}"
        ],
        [
            "",
            "\\mathbb{R}"
        ],
        [
            "",
            "\\beta_{\\delta}"
        ],
        [
            "",
            "\\boldsymbol{x}"
        ],
        [
            "",
            "\\mathbb{I}"
        ],
        [
            "",
            "\\bar{\\mathbb{I}}"
        ],
        [
            "",
            "\\boldsymbol{x}"
        ],
        [
            "",
            "\\mathbb{I}"
        ],
        [
            "",
            "\\boldsymbol{x}"
        ],
        [
            "",
            "\\mathbb{I}"
        ],
        [
            "",
            "\\bar{\\mathbb{I}}"
        ],
        [
            "",
            "\\boldsymbol{x}"
        ],
        [
            "",
            "\\mathbb{I}"
        ],
        [
            "",
            "\\boldsymbol{x}"
        ],
        [
            "",
            "\\mathbb{I}"
        ],
        [
            "",
            "\\bar{\\mathbb{I}}"
        ],
        [
            "",
            "\\boldsymbol{x}"
        ],
        [
            "",
            "\\mathbb{I}"
        ],
        [
            "",
            "\\sigma_{\\omega}"
        ],
        [
            "",
            "\\sigma_{\\text{prior}}"
        ],
        [
            "",
            "\\vartheta_{il}"
        ],
        [
            "",
            "\\mathcal{S}"
        ],
        [
            "",
            "\\sum_{l\\in\\mathcal{S}_i}"
        ],
        [
            "",
            "\\sigma_{\\text{prior}}"
        ],
        [
            "",
            "\\bm{x}"
        ],
        [
            "",
            "\\mu_i"
        ],
        [
            "",
            "\\bm{f}"
        ],
        [
            "",
            "\\bm{x}"
        ],
        [
            "",
            "\\bm{x}"
        ],
        [
            "",
            "\\boldsymbol{X}"
        ],
        [
            "",
            "\\boldsymbol{x}"
        ],
        [
            "",
            "\\mathbb{I}"
        ],
        [
            "",
            "\\bar{\\mathbb{I}}"
        ],
        [
            "",
            "\\boldsymbol{X}"
        ],
        [
            "",
            "\\mathbb{I}"
        ],
        [
            "",
            "\\bar{\\mathbb{I}}"
        ],
        [
            "",
            "\\mathbb{I}"
        ],
        [
            "",
            "\\bar{\\mathbb{I}}"
        ],
        [
            "",
            "\\mathbb{R}"
        ],
        [
            "",
            "\\omega_i"
        ],
        [
            "",
            "\\sigma_{\\omega_i}"
        ],
        [
            "",
            "\\omega_i"
        ],
        [
            "",
            "\\sigma_{\\omega_i}"
        ],
        [
            "",
            "\\omega_{i,k}"
        ],
        [
            "",
            "\\boldsymbol{x}"
        ],
        [
            "",
            "\\bm{e}"
        ],
        [
            "",
            "\\bm{x}"
        ],
        [
            "",
            "\\bm{x}"
        ],
        [
            "",
            "\\mathbb{I}"
        ],
        [
            "",
            "\\bar{\\mathbb{I}}"
        ],
        [
            "",
            "\\sum_{p \\in \\bar{\\mathbb{I}}_i(t_k,\\rho)}"
        ],
        [
            "",
            "\\sigma_{\\omega}"
        ],
        [
            "",
            "\\mathbb{X}"
        ],
        [
            "",
            "\\boldsymbol{x}"
        ],
        [
            "",
            "\\boldsymbol{f}"
        ],
        [
            "",
            "\\bm{X}"
        ],
        [
            "",
            "\\bm{x}"
        ],
        [
            "",
            "\\bm{k}"
        ],
        [
            "",
            "\\bm{X}"
        ],
        [
            "",
            "\\bm{x}"
        ],
        [
            "",
            "\\bm{k}"
        ],
        [
            "\\todo",
            "\\todo{}"
        ]
    ]
}
